runesmith/__init__.py
runesmith/__main__.py
runesmith/cli.py
runesmith/crawler.py
runesmith/llm.py
runesmith-0.1.0.dist-info/METADATA
runesmith-0.1.0.dist-info/WHEEL
runesmith-0.1.0.dist-info/entry_points.txt
runesmith-0.1.0.dist-info/RECORD
