Metadata-Version: 2.4
Name: runesmith
Version: 0.1.0
Summary: **runesmith** is a CLI tool for generating and updating documentation for codebases or single files using OpenAI's API and other LLM providers.
Author-email: Yao Ke <yaoke259@outlook.com>
Requires-Python: >=3.10
Requires-Dist: ollama>=0.4.8
Requires-Dist: openai>=1.75.0
Requires-Dist: pathspec>=0.12.1
Requires-Dist: python-dotenv>=1.1.0
Requires-Dist: pyyaml>=6.0.2
Requires-Dist: questionary>=2.1.0
Requires-Dist: rich>=14.0.0
Requires-Dist: tiktoken>=0.9.0
Requires-Dist: typer>=0.15.2
